ardj/__init__.py
ardj/__main__.py
ardj/auth.py
ardj/chat.py
ardj/config.py
ardj/console.py
ardj/database.py
ardj/database_mysql.py
ardj/database_sqlite.py
ardj/ezstream.py
ardj/icecast.py
ardj/ices.py
ardj/listeners.py
ardj/log.py
ardj/models.py
ardj/playlist.py
ardj/replaygain.py
ardj/scrobbler.py
ardj/server.py
ardj/tags.py
ardj/tracks.py
ardj/users.py
ardj/util.py
ardj/uwsgi.py
ardj/webclient.py
ardj/worker.py
ardj/data/cubic_undead.mp3
ardj/data/mysql_init.sql
ardj/data/screen.rc
ardj/data/sqlite_init.sql
ardj/data/stefano_mocini_leaving_you_failure_edit.ogg
ardj/data/successful_install.ogg
ardj/data/webroot/auth.html
ardj/data/webroot/favicon.ico
ardj/data/webroot/docs/index.html
ardj/data/webroot/docs/install.html
ardj/data/webroot/docs/manual.html
ardj/data/webroot/docs/playlists.html
ardj/data/webroot/docs/queue.html
ardj/data/webroot/fonts/glyphicons-halflings-regular.eot
ardj/data/webroot/fonts/glyphicons-halflings-regular.svg
ardj/data/webroot/fonts/glyphicons-halflings-regular.ttf
ardj/data/webroot/fonts/glyphicons-halflings-regular.woff
ardj/data/webroot/fonts/glyphicons-halflings-regular.woff2
ardj/data/webroot/images/download.png
ardj/data/webroot/images/queue.png
ardj/data/webroot/images/rocks.png
ardj/data/webroot/images/sucks.png
ardj/data/webroot/scripts/ardj-web-ui.js
ardj/data/webroot/scripts/ardj.js
ardj/data/webroot/scripts/async.js
ardj/data/webroot/scripts/bootstrap.min.js
ardj/data/webroot/scripts/jquery-1.11.2.min.js
ardj/data/webroot/scripts/np.js
ardj/data/webroot/scripts/player.js
ardj/data/webroot/styles/bootstrap-theme.css
ardj/data/webroot/styles/bootstrap.min.css
ardj/data/webroot/styles/screen.css
ardj/data/webroot/templates/base.tpl
ardj/data/webroot/templates/index.tpl
ardj/data/webroot/templates/playlist.tpl
ardj/data/webroot/templates/track.tpl
ardj/data/webroot/templates/upload.tpl
ardj-2.0.14.data/scripts/ardj
ardj-2.0.14.data/scripts/ardj-ezmeta
ardj-2.0.14.dist-info/DESCRIPTION.rst
ardj-2.0.14.dist-info/METADATA
ardj-2.0.14.dist-info/RECORD
ardj-2.0.14.dist-info/WHEEL
ardj-2.0.14.dist-info/metadata.json
ardj-2.0.14.dist-info/top_level.txt
