Metadata-Version: 2.0
Name: ardj
Version: 2.0.14
Summary: An artificial DJ for you internet radio.
Home-page: http://umonkey.net/ardj/
Author: Justin Forest
Author-email: hex@umonkey.net
License: GNU GPL
Platform: UNKNOWN
Classifier: License :: OSI Approved :: GNU General Public License (GPL)
Classifier: Natural Language :: English
Classifier: Operating System :: Unix
Classifier: Programming Language :: Python
Classifier: Topic :: Internet
Requires-Dist: Jinja2
Requires-Dist: PyYAML
Requires-Dist: mutagen
Requires-Dist: mysql
Requires-Dist: oauth2
Requires-Dist: setuptools
Requires-Dist: web.py
